nginx_conf_parser/__init__.py
nginx_conf_parser/context.py
nginx_conf_parser/events_context.py
nginx_conf_parser/http_context.py
nginx_conf_parser/main_context.py
nginx_conf_parser/server_context.py
nginx_conf_parser/stream_context.py
nginx_conf_parser/upstream_context.py
nginx_conf_parser/utils.py
nginx_conf_parser-0.1.1.dist-info/LICENSE
nginx_conf_parser-0.1.1.dist-info/WHEEL
nginx_conf_parser-0.1.1.dist-info/METADATA
nginx_conf_parser-0.1.1.dist-info/RECORD
